Metadata-Version: 2.1
Name: ImageStega
Version: 0.0.1
Summary: A package for Image steganography
Home-page: UNKNOWN
Author: Atharva Vidwans
Author-email: atharvavidwans@gmail.com
License: MIT
Platform: UNKNOWN
Classifier: Development Status :: 5 - Production/Stable
Classifier: Intended Audience :: Education
Classifier: Operating System :: Microsoft :: Windows :: Windows 10
Classifier: License :: OSI Approved :: MIT License
Classifier: Programming Language :: Python :: 3
